rdaensemble/__init__.py
rdaensemble/general/__init__.py
rdaensemble/general/metautils.py
rdaensemble/general/notable_maps.py
rdaensemble/general/score.py
rdaensemble/general/utils.py
rdaensemble/mcmc/__init__.py
rdaensemble/mcmc/metrics.py
rdaensemble/mcmc/optimized.py
rdaensemble/mcmc/prep_data.py
rdaensemble/mcmc/run_chain.py
rdaensemble/mcmc/setup_chain.py
rdaensemble/rmfrsp/__init__.py
rdaensemble/rmfrsp/ensemble.py
rdaensemble/rmfrst/__init__.py
rdaensemble/rmfrst/ensemble.py
rdaensemble/rmfrst/random_map.py
rdaensemble/smc/__init__.py
rdaensemble/ust/__init__.py
rdaensemble/ust/graph.py
rdaensemble/ust/ust.py
rdaensemble-2.0.2.dist-info/LICENSE
rdaensemble-2.0.2.dist-info/METADATA
rdaensemble-2.0.2.dist-info/WHEEL
rdaensemble-2.0.2.dist-info/top_level.txt
rdaensemble-2.0.2.dist-info/RECORD
